efsync/__init__.py
efsync/efsync_cli.py
efsync/logger.py
efsync/main.py
efsync/test/__init__.py
efsync/test/test_main.py
efsync/test/test_utils.py
efsync/utils/__init__.py
efsync/utils/config/__init__.py
efsync/utils/config/get_boto3_client.py
efsync/utils/config/load_args_from_yaml.py
efsync/utils/config/load_config.py
efsync/utils/config/read_requirements_from_file.py
efsync/utils/config/validate_config.py
efsync/utils/ec2/__init__.py
efsync/utils/ec2/create_user_data.py
efsync/utils/ec2/custom_waiter.py
efsync/utils/ec2/ec2_main.py
efsync/utils/ec2/ec2_waiter.py
efsync/utils/efs/__init__.py
efsync/utils/efs/describe_efs.py
efsync/utils/iam_profile/__init__.py
efsync/utils/iam_profile/iam_profile.py
efsync/utils/security_group/__init__.py
efsync/utils/security_group/ec2_security_group.py
efsync/utils/ssh/__init__.py
efsync/utils/ssh/createSSHClient.py
efsync/utils/ssh/scp_to_ec2.py
efsync/utils/ssh/ssh_key.py
efsync-1.0.3.dist-info/LICENSE
efsync-1.0.3.dist-info/METADATA
efsync-1.0.3.dist-info/WHEEL
efsync-1.0.3.dist-info/entry_points.txt
efsync-1.0.3.dist-info/top_level.txt
efsync-1.0.3.dist-info/RECORD
